{
  "defaultLanguage": "en-US",
  "languages": {
    "en-US": {
      "_": "English (US)",
      "hello": "Hello! I am Frust Time.",
      "test": "At the next sound, about 5 weeks, 4 days, 3 hours, and 2 minutes remain.",
      "peep": "peep!",
      "sorry": "Sorry, I'm unable to get your remaining time. Maybe your time is already over or your holder decided not to let you know anymore. , ! , I'll try again later.",
      "error": "I'm currently getting an error from the EmlaLock API. , ! , Please check your credentials and internet connection. , ! , I'll try again later.",
      "noSession": "It seems you're not in a session right now. , ! , I'll try again later.",
      "week": "Week",
      "weeks": "Weeks",
      "day": "Day",
      "days": "Days",
      "hour": "Hour",
      "hours": "Hours",
      "minute": "Minute",
      "minutes": "Minutes",
      "greeting": "Welcome, {user}!",
      "time": "At the next sound, about {time} remain."
    },
    "en-GB": {
      "_": "English (GB)",
      "hello": "Hello! I am Frust Time.",
      "test": "I'm happy to tell you that, at the next sound, about 5 weeks, 4 days, 3 hours, and 2 minutes remain.",
      "peep": "tea!",
      "sorry": "Sorry, I'm unable to get your remaining time. Maybe your time is already over or your holder decided not to let you know anymore. , ! , I'll try again later.",
      "error": "I'm currently getting an error from the EmlaLock API. , ! , Please check your credentials and internet connection. , ! , I'll try again later.",
      "noSession": "It seems you're not in a session right now. , ! , I'll try again later.",
      "week": "Week",
      "weeks": "Weeks",
      "day": "Day",
      "days": "Days",
      "hour": "Hour",
      "hours": "Hours",
      "minute": "Minute",
      "minutes": "Minutes",
      "greeting": "A warm welcome for you, {user}!",
      "time": "I'm happy to tell you that at the next sound, about {time} remain."
    },
    "de-DE": {
      "_": "Deutsch",
      "_delta": 3,
      "hello": "Hallo! Ich bin Frust Zeit.",
      "test": "Beim nächsten Ton verbleiben 5 Wochen, 4 Tage, 3 Stunden und 2 Minuten.",
      "peep": "Piep!",
      "sorry": "Entschuldige, ich kann aktuell Deine Rest-Zeit nicht lesen. Vielleicht ist Deine Zeit vorbei oder Dein Holder hat beschlossen, dass Du es nicht mehr wissen sollst. , ! , Ich versuche es später noch einmal.",
      "error": "Ich erhalte aktuell eine Fehlermeldung von der EmlaLock API. , ! , Bitte prüfe Deine Zugangsdaten und die Internetverbindung. , ! , Ich versuche es später noch einmal.",
      "noSession": "Scheinbar bist Du gerade in keiner Sitzung. , ! , Ich versuche es später noch einmal.",
      "week": "Woche",
      "weeks": "Wochen",
      "day": "Tag",
      "days": "Tage",
      "hour": "Stunde",
      "hours": "Stunden",
      "minute": "Minute",
      "minutes": "Minuten",
      "greeting": "Willkommen, {user}!",
      "time": "Beim nächsten Ton verbleiben in etwa {time}."
    },
    "nl-NL": {
      "_": "Nederlands",
      "_delta": 4,
      "hallo": "Hallo! Ik ben frustratie tijd.",
      "test": "bij het volgende geluid, nog ongeveer 5 weken, 4 dagen, 3 uur, en 2 minuten te gaan.",
      "peep": "peep!",
      "sorry": "Sorry, ik kan je tijd die nog over is niet zien. Misschien is je tijd al om of heeft je houder besloten de tijd te verbergen. , ! , ik probeer het later nog een keer.",
      "error": "ik kreeg momenteel een error van de EmlaLock API. , ! , check alsjeblieft je settings of je connectie. , ! , ik probeer het later nog een keer.",
      "noSession": "het lijkt erop dat je momenteel niet in een sessie zit. , ! , ik probeer het later nog een keer.",
      "week": "Week",
      "weeks": "Weken",
      "day": "dag",
      "days": "dagen",
      "hour": "uur",
      "hours": "uren",
      "minute": "minuut",
      "minutes": "minuten",
      "greeting": "Welkom, {user}!",
      "time": "Bij het volgende geluid, is er nog {time} te gaan."
    }
  }
}
